{
  "key": "stats_squads_gca_against",
  "value": [
    {
      "Squad": "vs Atalanta",
      "# Pl": "32",
      "90s": "38.0",
      "SCA": "697",
      "SCA90": "18.34",
      "PassLive": "44",
      "PassDead": "4",
      "TO": "4",
      "Sh": "4",
      "Fld": "2",
      "Def": "2",
      "GCA": "60",
      "GCA90": "1.58"
    },
    {
      "Squad": "vs Bologna",
      "# Pl": "30",
      "90s": "38.0",
      "SCA": "571",
      "SCA90": "15.03",
      "PassLive": "58",
      "PassDead": "4",
      "TO": "8",
      "Sh": "7",
      "Fld": "2",
      "Def": "0",
      "GCA": "79",
      "GCA90": "2.08"
    },
    {
      "Squad": "vs Cagliari",
      "# Pl": "28",
      "90s": "38.0",
      "SCA": "890",
      "SCA90": "23.42",
      "PassLive": "64",
      "PassDead": "7",
      "TO": "7",
      "Sh": "15",
      "Fld": "5",
      "Def": "1",
      "GCA": "99",
      "GCA90": "2.61"
    },
    {
      "Squad": "vs Como",
      "# Pl": "38",
      "90s": "38.0",
      "SCA": "655",
      "SCA90": "17.24",
      "PassLive": "65",
      "PassDead": "5",
      "TO": "7",
      "Sh": "6",
      "Fld": "5",
      "Def": "2",
      "GCA": "90",
      "GCA90": "2.37"
    },
    {
      "Squad": "vs Empoli",
      "# Pl": "34",
      "90s": "38.0",
      "SCA": "916",
      "SCA90": "24.11",
      "PassLive": "75",
      "PassDead": "5",
      "TO": "5",
      "Sh": "10",
      "Fld": "2",
      "Def": "3",
      "GCA": "100",
      "GCA90": "2.63"
    },
    {
      "Squad": "vs Fiorentina",
      "# Pl": "34",
      "90s": "38.0",
      "SCA": "767",
      "SCA90": "20.19",
      "PassLive": "51",
      "PassDead": "2",
      "TO": "6",
      "Sh": "3",
      "Fld": "2",
      "Def": "1",
      "GCA": "65",
      "GCA90": "1.71"
    },
    {
      "Squad": "vs Genoa",
      "# Pl": "37",
      "90s": "38.0",
      "SCA": "853",
      "SCA90": "22.45",
      "PassLive": "60",
      "PassDead": "5",
      "TO": "4",
      "Sh": "7",
      "Fld": "3",
      "Def": "0",
      "GCA": "79",
      "GCA90": "2.08"
    },
    {
      "Squad": "vs Hellas Verona",
      "# Pl": "32",
      "90s": "38.0",
      "SCA": "900",
      "SCA90": "23.68",
      "PassLive": "78",
      "PassDead": "6",
      "TO": "7",
      "Sh": "12",
      "Fld": "1",
      "Def": "2",
      "GCA": "106",
      "GCA90": "2.79"
    },
    {
      "Squad": "vs Inter",
      "# Pl": "26",
      "90s": "38.0",
      "SCA": "710",
      "SCA90": "18.69",
      "PassLive": "37",
      "PassDead": "2",
      "TO": "6",
      "Sh": "8",
      "Fld": "2",
      "Def": "1",
      "GCA": "56",
      "GCA90": "1.47"
    },
    {
      "Squad": "vs Juventus",
      "# Pl": "29",
      "90s": "38.0",
      "SCA": "681",
      "SCA90": "17.92",
      "PassLive": "42",
      "PassDead": "3",
      "TO": "0",
      "Sh": "5",
      "Fld": "6",
      "Def": "0",
      "GCA": "56",
      "GCA90": "1.47"
    },
    {
      "Squad": "vs Lazio",
      "# Pl": "27",
      "90s": "38.0",
      "SCA": "683",
      "SCA90": "17.97",
      "PassLive": "63",
      "PassDead": "4",
      "TO": "2",
      "Sh": "5",
      "Fld": "3",
      "Def": "1",
      "GCA": "78",
      "GCA90": "2.05"
    },
    {
      "Squad": "vs Lecce",
      "# Pl": "31",
      "90s": "38.0",
      "SCA": "932",
      "SCA90": "24.53",
      "PassLive": "62",
      "PassDead": "4",
      "TO": "6",
      "Sh": "11",
      "Fld": "12",
      "Def": "3",
      "GCA": "98",
      "GCA90": "2.58"
    },
    {
      "Squad": "vs Milan",
      "# Pl": "35",
      "90s": "38.0",
      "SCA": "776",
      "SCA90": "20.42",
      "PassLive": "50",
      "PassDead": "6",
      "TO": "3",
      "Sh": "6",
      "Fld": "5",
      "Def": "1",
      "GCA": "71",
      "GCA90": "1.87"
    },
    {
      "Squad": "vs Monza",
      "# Pl": "36",
      "90s": "38.0",
      "SCA": "1020",
      "SCA90": "26.84",
      "PassLive": "91",
      "PassDead": "10",
      "TO": "9",
      "Sh": "7",
      "Fld": "6",
      "Def": "1",
      "GCA": "124",
      "GCA90": "3.26"
    },
    {
      "Squad": "vs Napoli",
      "# Pl": "27",
      "90s": "38.0",
      "SCA": "643",
      "SCA90": "16.92",
      "PassLive": "35",
      "PassDead": "0",
      "TO": "2",
      "Sh": "3",
      "Fld": "2",
      "Def": "1",
      "GCA": "43",
      "GCA90": "1.13"
    },
    {
      "Squad": "vs Parma",
      "# Pl": "32",
      "90s": "38.0",
      "SCA": "986",
      "SCA90": "25.95",
      "PassLive": "72",
      "PassDead": "5",
      "TO": "2",
      "Sh": "11",
      "Fld": "7",
      "Def": "0",
      "GCA": "97",
      "GCA90": "2.55"
    },
    {
      "Squad": "vs Roma",
      "# Pl": "28",
      "90s": "38.0",
      "SCA": "757",
      "SCA90": "19.92",
      "PassLive": "33",
      "PassDead": "6",
      "TO": "2",
      "Sh": "7",
      "Fld": "5",
      "Def": "0",
      "GCA": "53",
      "GCA90": "1.39"
    },
    {
      "Squad": "vs Torino",
      "# Pl": "31",
      "90s": "38.0",
      "SCA": "926",
      "SCA90": "24.37",
      "PassLive": "50",
      "PassDead": "6",
      "TO": "5",
      "Sh": "7",
      "Fld": "5",
      "Def": "2",
      "GCA": "75",
      "GCA90": "1.97"
    },
    {
      "Squad": "vs Udinese",
      "# Pl": "31",
      "90s": "38.0",
      "SCA": "867",
      "SCA90": "22.82",
      "PassLive": "57",
      "PassDead": "4",
      "TO": "2",
      "Sh": "14",
      "Fld": "8",
      "Def": "0",
      "GCA": "85",
      "GCA90": "2.24"
    },
    {
      "Squad": "vs Venezia",
      "# Pl": "36",
      "90s": "38.0",
      "SCA": "987",
      "SCA90": "25.97",
      "PassLive": "57",
      "PassDead": "10",
      "TO": "3",
      "Sh": "9",
      "Fld": "10",
      "Def": "4",
      "GCA": "93",
      "GCA90": "2.45"
    }
  ]
}